treen/__init__.py
treen-0.0.1.dist-info/METADATA
treen-0.0.1.dist-info/WHEEL
treen-0.0.1.dist-info/top_level.txt
treen-0.0.1.dist-info/RECORD
