Metadata-Version: 2.1
Name: treen
Version: 0.0.1
Summary: A Python library for energy forecasting using decision trees.
Author: rebase.energy
